odoo/addons/sale_order_customer_free_ref/README.rst
odoo/addons/sale_order_customer_free_ref/__init__.py
odoo/addons/sale_order_customer_free_ref/__manifest__.py
odoo/addons/sale_order_customer_free_ref/i18n/es.po
odoo/addons/sale_order_customer_free_ref/i18n/sale_order_customer_free_ref.pot
odoo/addons/sale_order_customer_free_ref/models/__init__.py
odoo/addons/sale_order_customer_free_ref/models/account_move.py
odoo/addons/sale_order_customer_free_ref/models/sale_order.py
odoo/addons/sale_order_customer_free_ref/readme/CONTRIBUTORS.rst
odoo/addons/sale_order_customer_free_ref/readme/CREDITS.rst
odoo/addons/sale_order_customer_free_ref/readme/DESCRIPTION.rst
odoo/addons/sale_order_customer_free_ref/static/description/icon.png
odoo/addons/sale_order_customer_free_ref/static/description/index.html
odoo/addons/sale_order_customer_free_ref/tests/__init__.py
odoo/addons/sale_order_customer_free_ref/tests/test_sale_order_customer_free_ref.py
odoo/addons/sale_order_customer_free_ref/views/account_move.xml
odoo/addons/sale_order_customer_free_ref/views/sale_order.xml
odoo14_addon_sale_order_customer_free_ref-14.0.1.0.1.dist-info/METADATA
odoo14_addon_sale_order_customer_free_ref-14.0.1.0.1.dist-info/WHEEL
odoo14_addon_sale_order_customer_free_ref-14.0.1.0.1.dist-info/top_level.txt
odoo14_addon_sale_order_customer_free_ref-14.0.1.0.1.dist-info/RECORD
