Metadata-Version: 2.1
Name: odoo14-addon-sale-order-customer-free-ref
Version: 14.0.1.0.1
Summary: Splits the Customer Reference on sale orders into two fields. An Id and a Free reference. The existing field is transformed into a computed one.
Home-page: https://github.com/OCA/edi
Author: Camptocamp, Odoo Community Association (OCA)
Author-email: support@odoo-community.org
License: AGPL-3
Platform: UNKNOWN
Classifier: Programming Language :: Python
Classifier: Framework :: Odoo
Classifier: Framework :: Odoo :: 14.0
Classifier: License :: OSI Approved :: GNU Affero General Public License v3
Requires-Python: >=3.6
Requires-Dist: odoo <14.1dev,>=14.0a
